LICENSE
README.md
nautobot_plugin_chatops_panorama/__init__.py
nautobot_plugin_chatops_panorama/constant.py
nautobot_plugin_chatops_panorama/jinja_filters.py
nautobot_plugin_chatops_panorama/static/nautobot_palo/palo-alto-networks.png
nautobot_plugin_chatops_panorama/static/nautobot_palo/palo_resized.png
nautobot_plugin_chatops_panorama/static/nautobot_palo/palo_transparent.png
nautobot_plugin_chatops_panorama/tests/__init__.py
nautobot_plugin_chatops_panorama/tests/test_basic.py
nautobot_plugin_chatops_panorama/tests/test_utils_panorama.py
nautobot_plugin_chatops_panorama/utils/__init__.py
nautobot_plugin_chatops_panorama/utils/panorama.py
nautobot_plugin_chatops_panorama/worker.py
nautobot_plugin_chatops_panorama-1.2.0.dist-info/LICENSE
nautobot_plugin_chatops_panorama-1.2.0.dist-info/METADATA
nautobot_plugin_chatops_panorama-1.2.0.dist-info/WHEEL
nautobot_plugin_chatops_panorama-1.2.0.dist-info/entry_points.txt
nautobot_plugin_chatops_panorama-1.2.0.dist-info/RECORD
