Metadata-Version: 2.1
Name: nautobot-plugin-chatops-panorama
Version: 1.2.0
Summary: Nautobot Chatops plugin for Panorama
Home-page: https://github.com/nautobot/nautobot-plugin-chatops-panorama
License: Apache-2.0
Keywords: nautobot,nautobot-plugin,nautobot-chatops-plugin
Author: Network to Code, LLC
Author-email: opensource@networktocode.com
Requires-Python: >=3.7,<4.0
Classifier: License :: OSI Approved :: Apache Software License
Classifier: Programming Language :: Python :: 3
Classifier: Programming Language :: Python :: 3.7
Classifier: Programming Language :: Python :: 3.8
Classifier: Programming Language :: Python :: 3.9
Classifier: Programming Language :: Python :: 3.10
Classifier: Programming Language :: Python :: 3.11
Provides-Extra: nautobot
Requires-Dist: Markdown
Requires-Dist: defusedxml
Requires-Dist: importlib-metadata (==4.13.0)
Requires-Dist: ipaddr
Requires-Dist: nautobot (>=1.4.0,<2.0.0) ; extra == "nautobot"
Requires-Dist: nautobot-chatops (>=1.11.0,<2.0.0)
Requires-Dist: netmiko
Requires-Dist: pan-os-python (>=1.3.0,<2.0.0)
Requires-Dist: requests
Project-URL: Repository, https://github.com/nautobot/nautobot-plugin-chatops-panorama
